kivy/__init__.py
kivy/_clock.cp38-win_amd64.pyd
kivy/_clock.pxd
kivy/_event.cp38-win_amd64.pyd
kivy/_event.pxd
kivy/_metrics.cp38-win_amd64.pyd
kivy/_metrics.pxd
kivy/_version.py
kivy/animation.py
kivy/app.py
kivy/atlas.py
kivy/base.py
kivy/cache.py
kivy/clock.py
kivy/compat.py
kivy/config.py
kivy/context.py
kivy/event.py
kivy/factory.py
kivy/factory_registers.py
kivy/geometry.py
kivy/gesture.py
kivy/interactive.py
kivy/loader.py
kivy/logger.py
kivy/metrics.py
kivy/multistroke.py
kivy/parser.py
kivy/properties.cp38-win_amd64.pyd
kivy/properties.pxd
kivy/resources.py
kivy/setupconfig.py
kivy/support.py
kivy/utils.py
kivy/vector.py
kivy/weakmethod.py
kivy/weakproxy.cp38-win_amd64.pyd
kivy/core/__init__.py
kivy/core/audio/__init__.py
kivy/core/audio/audio_android.py
kivy/core/audio/audio_avplayer.py
kivy/core/audio/audio_ffpyplayer.py
kivy/core/audio/audio_gstplayer.py
kivy/core/audio/audio_pygame.py
kivy/core/audio/audio_sdl2.cp38-win_amd64.pyd
kivy/core/camera/__init__.py
kivy/core/camera/camera_android.py
kivy/core/camera/camera_gi.py
kivy/core/camera/camera_opencv.py
kivy/core/camera/camera_picamera.py
kivy/core/clipboard/__init__.py
kivy/core/clipboard/_clipboard_ext.py
kivy/core/clipboard/_clipboard_sdl2.cp38-win_amd64.pyd
kivy/core/clipboard/clipboard_android.py
kivy/core/clipboard/clipboard_dbusklipper.py
kivy/core/clipboard/clipboard_dummy.py
kivy/core/clipboard/clipboard_gtk3.py
kivy/core/clipboard/clipboard_nspaste.py
kivy/core/clipboard/clipboard_pygame.py
kivy/core/clipboard/clipboard_sdl2.py
kivy/core/clipboard/clipboard_winctypes.py
kivy/core/clipboard/clipboard_xclip.py
kivy/core/clipboard/clipboard_xsel.py
kivy/core/gl/__init__.py
kivy/core/image/__init__.py
kivy/core/image/_img_sdl2.cp38-win_amd64.pyd
kivy/core/image/img_dds.py
kivy/core/image/img_ffpyplayer.py
kivy/core/image/img_pil.py
kivy/core/image/img_pygame.py
kivy/core/image/img_sdl2.py
kivy/core/image/img_tex.py
kivy/core/spelling/__init__.py
kivy/core/spelling/spelling_enchant.py
Kivy-2.3.1.dist-info/AUTHORS
Kivy-2.3.1.dist-info/LICENSE
Kivy-2.3.1.dist-info/METADATA
Kivy-2.3.1.dist-info/WHEEL
Kivy-2.3.1.dist-info/dependency_links.txt
Kivy-2.3.1.dist-info/top_level.txt
Kivy-2.3.1.dist-info/RECORD
