Metadata-Version: 2.1
Name: Kivy
Version: 2.3.1
Summary: An open-source Python framework for developing GUI apps that work cross-platform, including desktop, mobile and embedded platforms.
Home-page: http://kivy.org
Author: Kivy Team and other contributors
Author-email: kivy-dev@googlegroups.com
License: MIT
Project-URL: Source, https://github.com/kivy/kivy
Project-URL: Documentation, https://kivy.org/doc/stable/
Project-URL: Bug Reports, https://github.com/kivy/kivy/issues
Classifier: Development Status :: 5 - Production/Stable
Classifier: Environment :: MacOS X
Classifier: Environment :: Win32 (MS Windows)
Classifier: Environment :: X11 Applications
Classifier: Intended Audience :: Developers
Classifier: Intended Audience :: End Users/Desktop
Classifier: Intended Audience :: Information Technology
Classifier: Intended Audience :: Science/Research
Classifier: License :: OSI Approved :: MIT License
Classifier: Natural Language :: English
Classifier: Operating System :: MacOS :: MacOS X
Classifier: Operating System :: Microsoft :: Windows
Classifier: Operating System :: POSIX :: BSD :: FreeBSD
Classifier: Operating System :: POSIX :: Linux
Classifier: Programming Language :: Python :: 3.8
Classifier: Programming Language :: Python :: 3.9
Classifier: Programming Language :: Python :: 3.10
Classifier: Programming Language :: Python :: 3.11
Classifier: Programming Language :: Python :: 3.12
Classifier: Programming Language :: Python :: 3.13
Classifier: Topic :: Artistic Software
Classifier: Topic :: Games/Entertainment
Classifier: Topic :: Multimedia :: Graphics :: 3D Rendering
Classifier: Topic :: Multimedia :: Graphics :: Capture :: Digital Camera
Classifier: Topic :: Multimedia :: Graphics :: Presentation
Classifier: Topic :: Multimedia :: Graphics :: Viewers
Classifier: Topic :: Multimedia :: Sound/Audio :: Players :: MP3
Classifier: Topic :: Multimedia :: Video :: Display
Classifier: Topic :: Scientific/Engineering :: Human Machine Interfaces
Classifier: Topic :: Scientific/Engineering :: Visualization
Classifier: Topic :: Software Development :: Libraries :: Application Frameworks
Classifier: Topic :: Software Development :: User Interfaces
Requires-Python: >=3.8
License-File: LICENSE
License-File: AUTHORS
Requires-Dist: Kivy-Garden>=0.1.4
Requires-Dist: docutils
Requires-Dist: pygments
Requires-Dist: requests
Requires-Dist: filetype
Requires-Dist: kivy_deps.angle~=0.4.0; sys_platform == "win32"
Requires-Dist: kivy_deps.sdl2~=0.8.0; sys_platform == "win32"
Requires-Dist: kivy_deps.glew~=0.3.1; sys_platform == "win32"
Requires-Dist: pypiwin32; sys_platform == "win32"
Provides-Extra: tuio
Requires-Dist: oscpy; extra == "tuio"
Provides-Extra: dev
Requires-Dist: pytest>=3.6; extra == "dev"
Requires-Dist: pytest-cov; extra == "dev"
Requires-Dist: pytest_asyncio!=0.11.0; extra == "dev"
Requires-Dist: pytest-timeout; extra == "dev"
Requires-Dist: pytest-benchmark; extra == "dev"
Requires-Dist: pyinstaller; extra == "dev"
Requires-Dist: sphinx~=6.2.1; extra == "dev"
Requires-Dist: sphinxcontrib-jquery~=4.1; extra == "dev"
Requires-Dist: kivy_deps.gstreamer_dev~=0.3.3; sys_platform == "win32" and extra == "dev"
Requires-Dist: kivy_deps.sdl2_dev~=0.8.0; sys_platform == "win32" and extra == "dev"
Requires-Dist: kivy_deps.glew_dev~=0.3.1; sys_platform == "win32" and extra == "dev"
Requires-Dist: flake8; extra == "dev"
Requires-Dist: pre-commit; extra == "dev"
Requires-Dist: responses; extra == "dev"
Provides-Extra: base
Requires-Dist: pillow<11,>=9.5.0; extra == "base"
Provides-Extra: media
Requires-Dist: kivy_deps.gstreamer~=0.3.3; sys_platform == "win32" and extra == "media"
Requires-Dist: ffpyplayer; (sys_platform == "linux" or sys_platform == "darwin") and extra == "media"
Provides-Extra: full
Requires-Dist: pillow<11,>=9.5.0; extra == "full"
Requires-Dist: kivy_deps.gstreamer~=0.3.3; sys_platform == "win32" and extra == "full"
Requires-Dist: ffpyplayer; (sys_platform == "linux" or sys_platform == "darwin") and extra == "full"
Provides-Extra: gstreamer
Requires-Dist: kivy_deps.gstreamer~=0.3.3; sys_platform == "win32" and extra == "gstreamer"
Provides-Extra: angle
Requires-Dist: kivy_deps.angle~=0.4.0; sys_platform == "win32" and extra == "angle"
Provides-Extra: sdl2
Requires-Dist: kivy_deps.sdl2~=0.8.0; sys_platform == "win32" and extra == "sdl2"
Provides-Extra: glew
Requires-Dist: kivy_deps.glew~=0.3.1; sys_platform == "win32" and extra == "glew"
